[
	{
		"inputs": [
			{
				"internalType": "contract IRouter",
				"name": "_router",
				"type": "address"
			}
		],
		"stateMutability": "nonpayable",
		"type": "constructor"
	},
	{
		"anonymous": false,
		"inputs": [
			{
				"indexed": true,
				"internalType": "address",
				"name": "owner",
				"type": "address"
			},
			{
				"indexed": true,
				"internalType": "address",
				"name": "spender",
				"type": "address"
			},
			{
				"indexed": false,
				"internalType": "uint256",
				"name": "value",
				"type": "uint256"
			}
		],
		"name": "Approval",
		"type": "event"
	},
	{
		"anonymous": false,
		"inputs": [
			{
				"indexed": true,
				"internalType": "address",
				"name": "previousOwner",
				"type": "address"
			},
			{
				"indexed": true,
				"internalType": "address",
				"name": "newOwner",
				"type": "address"
			}
		],
		"name": "OwnershipTransferred",
		"type": "event"
	},
	{
		"anonymous": false,
		"inputs": [
			{
				"indexed": true,
				"internalType": "address",
				"name": "from",
				"type": "address"
			},
			{
				"indexed": true,
				"internalType": "address",
				"name": "to",
				"type": "address"
			},
			{
				"indexed": false,
				"internalType": "uint256",
				"name": "value",
				"type": "uint256"
			}
		],
		"name": "Transfer",
		"type": "event"
	},
	{
		"inputs": [
			{
				"internalType": "address",
				"name": "",
				"type": "address"
			}
		],
		"name": "admins",
		"outputs": [
			{
				"internalType": "bool",
				"name": "",
				"type": "bool"
			}
		],
		"stateMutability": "view",
		"type": "function"
	},
	{
		"inputs": [
			{
				"internalType": "address",
				"name": "owner",
				"type": "address"
			},
			{
				"internalType": "address",
				"name": "spender",
				"type": "address"
			}
		],
		"name": "allowance",
		"outputs": [
			{
				"internalType": "uint256",
				"name": "",
				"type": "uint256"
			}
		],
		"stateMutability": "view",
		"type": "function"
	},
	{
		"inputs": [
			{
				"internalType": "address",
				"name": "spender",
				"type": "address"
			},
			{
				"internalType": "uint256",
				"name": "amount",
				"type": "uint256"
			}
		],
		"name": "approve",
		"outputs": [
			{
				"internalType": "bool",
				"name": "",
				"type": "bool"
			}
		],
		"stateMutability": "nonpayable",
		"type": "function"
	},
	{
		"inputs": [
			{
				"internalType": "address",
				"name": "account",
				"type": "address"
			}
		],
		"name": "balanceOf",
		"outputs": [
			{
				"internalType": "uint256",
				"name": "",
				"type": "uint256"
			}
		],
		"stateMutability": "view",
		"type": "function"
	},
	{
		"inputs": [
			{
				"internalType": "address",
				"name": "account",
				"type": "address"
			}
		],
		"name": "blacklistReason",
		"outputs": [
			{
				"internalType": "string",
				"name": "",
				"type": "string"
			}
		],
		"stateMutability": "view",
		"type": "function"
	},
	{
		"inputs": [],
		"name": "buyFee",
		"outputs": [
			{
				"internalType": "uint16",
				"name": "",
				"type": "uint16"
			}
		],
		"stateMutability": "view",
		"type": "function"
	},
	{
		"inputs": [],
		"name": "buyLiquidityFee",
		"outputs": [
			{
				"internalType": "uint16",
				"name": "",
				"type": "uint16"
			}
		],
		"stateMutability": "view",
		"type": "function"
	},
	{
		"inputs": [],
		"name": "decimals",
		"outputs": [
			{
				"internalType": "uint8",
				"name": "",
				"type": "uint8"
			}
		],
		"stateMutability": "view",
		"type": "function"
	},
	{
		"inputs": [],
		"name": "disableLiquidityGeneration",
		"outputs": [],
		"stateMutability": "nonpayable",
		"type": "function"
	},
	{
		"inputs": [],
		"name": "fee",
		"outputs": [
			{
				"internalType": "uint16",
				"name": "",
				"type": "uint16"
			}
		],
		"stateMutability": "view",
		"type": "function"
	},
	{
		"inputs": [],
		"name": "feeWallet",
		"outputs": [
			{
				"internalType": "address",
				"name": "",
				"type": "address"
			}
		],
		"stateMutability": "view",
		"type": "function"
	},
	{
		"inputs": [],
		"name": "generateLiquidity",
		"outputs": [],
		"stateMutability": "nonpayable",
		"type": "function"
	},
	{
		"inputs": [
			{
				"internalType": "address",
				"name": "account",
				"type": "address"
			}
		],
		"name": "getAccountPeriodInfo",
		"outputs": [
			{
				"internalType": "uint256",
				"name": "startBalance",
				"type": "uint256"
			},
			{
				"internalType": "uint256",
				"name": "startTime",
				"type": "uint256"
			},
			{
				"internalType": "uint256",
				"name": "spent",
				"type": "uint256"
			}
		],
		"stateMutability": "view",
		"type": "function"
	},
	{
		"inputs": [],
		"name": "getOwner",
		"outputs": [
			{
				"internalType": "address",
				"name": "",
				"type": "address"
			}
		],
		"stateMutability": "view",
		"type": "function"
	},
	{
		"inputs": [
			{
				"internalType": "address",
				"name": "account",
				"type": "address"
			}
		],
		"name": "isBlacklisted",
		"outputs": [
			{
				"internalType": "bool",
				"name": "",
				"type": "bool"
			}
		],
		"stateMutability": "view",
		"type": "function"
	},
	{
		"inputs": [
			{
				"internalType": "address",
				"name": "account",
				"type": "address"
			}
		],
		"name": "isExcludedFromFee",
		"outputs": [
			{
				"internalType": "bool",
				"name": "",
				"type": "bool"
			}
		],
		"stateMutability": "view",
		"type": "function"
	},
	{
		"inputs": [
			{
				"internalType": "address",
				"name": "account",
				"type": "address"
			}
		],
		"name": "isSeller",
		"outputs": [
			{
				"internalType": "bool",
				"name": "",
				"type": "bool"
			}
		],
		"stateMutability": "view",
		"type": "function"
	},
	{
		"inputs": [
			{
				"internalType": "address",
				"name": "account",
				"type": "address"
			}
		],
		"name": "isWhitelisted",
		"outputs": [
			{
				"internalType": "bool",
				"name": "",
				"type": "bool"
			}
		],
		"stateMutability": "view",
		"type": "function"
	},
	{
		"inputs": [],
		"name": "liquidityFee",
		"outputs": [
			{
				"internalType": "uint16",
				"name": "",
				"type": "uint16"
			}
		],
		"stateMutability": "view",
		"type": "function"
	},
	{
		"inputs": [],
		"name": "marketingFee",
		"outputs": [
			{
				"internalType": "uint16",
				"name": "",
				"type": "uint16"
			}
		],
		"stateMutability": "view",
		"type": "function"
	},
	{
		"inputs": [],
		"name": "marketingWallet",
		"outputs": [
			{
				"internalType": "address",
				"name": "",
				"type": "address"
			}
		],
		"stateMutability": "view",
		"type": "function"
	},
	{
		"inputs": [],
		"name": "maxHodlPercent",
		"outputs": [
			{
				"internalType": "uint16",
				"name": "",
				"type": "uint16"
			}
		],
		"stateMutability": "view",
		"type": "function"
	},
	{
		"inputs": [],
		"name": "maxTransferPercent",
		"outputs": [
			{
				"internalType": "uint16",
				"name": "",
				"type": "uint16"
			}
		],
		"stateMutability": "view",
		"type": "function"
	},
	{
		"inputs": [],
		"name": "minTokensForLiquidityGeneration",
		"outputs": [
			{
				"internalType": "uint256",
				"name": "",
				"type": "uint256"
			}
		],
		"stateMutability": "view",
		"type": "function"
	},
	{
		"inputs": [],
		"name": "name",
		"outputs": [
			{
				"internalType": "string",
				"name": "",
				"type": "string"
			}
		],
		"stateMutability": "view",
		"type": "function"
	},
	{
		"inputs": [],
		"name": "owner",
		"outputs": [
			{
				"internalType": "address",
				"name": "",
				"type": "address"
			}
		],
		"stateMutability": "view",
		"type": "function"
	},
	{
		"inputs": [],
		"name": "pair",
		"outputs": [
			{
				"internalType": "address",
				"name": "",
				"type": "address"
			}
		],
		"stateMutability": "view",
		"type": "function"
	},
	{
		"inputs": [],
		"name": "periodDuration",
		"outputs": [
			{
				"internalType": "uint256",
				"name": "",
				"type": "uint256"
			}
		],
		"stateMutability": "view",
		"type": "function"
	},
	{
		"inputs": [],
		"name": "router",
		"outputs": [
			{
				"internalType": "contract IRouter",
				"name": "",
				"type": "address"
			}
		],
		"stateMutability": "view",
		"type": "function"
	},
	{
		"inputs": [],
		"name": "sellFee",
		"outputs": [
			{
				"internalType": "uint16",
				"name": "",
				"type": "uint16"
			}
		],
		"stateMutability": "view",
		"type": "function"
	},
	{
		"inputs": [],
		"name": "sellLiquidityFee",
		"outputs": [
			{
				"internalType": "uint16",
				"name": "",
				"type": "uint16"
			}
		],
		"stateMutability": "view",
		"type": "function"
	},
	{
		"inputs": [
			{
				"internalType": "address",
				"name": "account",
				"type": "address"
			},
			{
				"internalType": "bool",
				"name": "value",
				"type": "bool"
			}
		],
		"name": "setAdmin",
		"outputs": [],
		"stateMutability": "nonpayable",
		"type": "function"
	},
	{
		"inputs": [
			{
				"internalType": "address",
				"name": "account",
				"type": "address"
			},
			{
				"internalType": "bool",
				"name": "value",
				"type": "bool"
			},
			{
				"internalType": "string",
				"name": "reason",
				"type": "string"
			}
		],
		"name": "setBlacklist",
		"outputs": [],
		"stateMutability": "nonpayable",
		"type": "function"
	},
	{
		"inputs": [
			{
				"internalType": "address",
				"name": "_feeWallet",
				"type": "address"
			}
		],
		"name": "setFeeWallet",
		"outputs": [],
		"stateMutability": "nonpayable",
		"type": "function"
	},
	{
		"inputs": [
			{
				"internalType": "address",
				"name": "account",
				"type": "address"
			},
			{
				"internalType": "bool",
				"name": "value",
				"type": "bool"
			}
		],
		"name": "setFeeWhitelist",
		"outputs": [],
		"stateMutability": "nonpayable",
		"type": "function"
	},
	{
		"inputs": [
			{
				"internalType": "uint16",
				"name": "_liquidityFee",
				"type": "uint16"
			},
			{
				"internalType": "uint16",
				"name": "_buyLiquidityFee",
				"type": "uint16"
			},
			{
				"internalType": "uint16",
				"name": "_sellLiquidityFee",
				"type": "uint16"
			}
		],
		"name": "setLiquidityFees",
		"outputs": [],
		"stateMutability": "nonpayable",
		"type": "function"
	},
	{
		"inputs": [
			{
				"internalType": "address",
				"name": "token",
				"type": "address"
			}
		],
		"name": "setMainTokenInPair",
		"outputs": [],
		"stateMutability": "nonpayable",
		"type": "function"
	},
	{
		"inputs": [
			{
				"internalType": "uint16",
				"name": "_marketingFee",
				"type": "uint16"
			}
		],
		"name": "setMarketingFee",
		"outputs": [],
		"stateMutability": "nonpayable",
		"type": "function"
	},
	{
		"inputs": [
			{
				"internalType": "address",
				"name": "_marketingWallet",
				"type": "address"
			}
		],
		"name": "setMarketingWallet",
		"outputs": [],
		"stateMutability": "nonpayable",
		"type": "function"
	},
	{
		"inputs": [
			{
				"internalType": "uint16",
				"name": "percent",
				"type": "uint16"
			}
		],
		"name": "setMaxHodlPercent",
		"outputs": [],
		"stateMutability": "nonpayable",
		"type": "function"
	},
	{
		"inputs": [
			{
				"internalType": "uint16",
				"name": "percent",
				"type": "uint16"
			}
		],
		"name": "setMaxTransferPercent",
		"outputs": [],
		"stateMutability": "nonpayable",
		"type": "function"
	},
	{
		"inputs": [
			{
				"internalType": "uint256",
				"name": "amount",
				"type": "uint256"
			}
		],
		"name": "setMinTokensForLiquidityGeneration",
		"outputs": [],
		"stateMutability": "nonpayable",
		"type": "function"
	},
	{
		"inputs": [
			{
				"internalType": "address",
				"name": "_pair",
				"type": "address"
			}
		],
		"name": "setPair",
		"outputs": [],
		"stateMutability": "nonpayable",
		"type": "function"
	},
	{
		"inputs": [
			{
				"internalType": "uint256",
				"name": "time",
				"type": "uint256"
			}
		],
		"name": "setPeriodDuration",
		"outputs": [],
		"stateMutability": "nonpayable",
		"type": "function"
	},
	{
		"inputs": [
			{
				"internalType": "contract IRouter",
				"name": "_router",
				"type": "address"
			}
		],
		"name": "setRouter",
		"outputs": [],
		"stateMutability": "nonpayable",
		"type": "function"
	},
	{
		"inputs": [
			{
				"internalType": "address",
				"name": "account",
				"type": "address"
			},
			{
				"internalType": "bool",
				"name": "value",
				"type": "bool"
			}
		],
		"name": "setSeller",
		"outputs": [],
		"stateMutability": "nonpayable",
		"type": "function"
	},
	{
		"inputs": [
			{
				"internalType": "uint16",
				"name": "_fee",
				"type": "uint16"
			},
			{
				"internalType": "uint16",
				"name": "_buyFee",
				"type": "uint16"
			},
			{
				"internalType": "uint16",
				"name": "_sellFee",
				"type": "uint16"
			}
		],
		"name": "setTaxFees",
		"outputs": [],
		"stateMutability": "nonpayable",
		"type": "function"
	},
	{
		"inputs": [
			{
				"internalType": "address",
				"name": "account",
				"type": "address"
			},
			{
				"internalType": "bool",
				"name": "value",
				"type": "bool"
			}
		],
		"name": "setWhitelist",
		"outputs": [],
		"stateMutability": "nonpayable",
		"type": "function"
	},
	{
		"inputs": [],
		"name": "symbol",
		"outputs": [
			{
				"internalType": "string",
				"name": "",
				"type": "string"
			}
		],
		"stateMutability": "view",
		"type": "function"
	},
	{
		"inputs": [],
		"name": "totalSupply",
		"outputs": [
			{
				"internalType": "uint256",
				"name": "",
				"type": "uint256"
			}
		],
		"stateMutability": "view",
		"type": "function"
	},
	{
		"inputs": [
			{
				"internalType": "address",
				"name": "recipient",
				"type": "address"
			},
			{
				"internalType": "uint256",
				"name": "amount",
				"type": "uint256"
			}
		],
		"name": "transfer",
		"outputs": [
			{
				"internalType": "bool",
				"name": "",
				"type": "bool"
			}
		],
		"stateMutability": "nonpayable",
		"type": "function"
	},
	{
		"inputs": [
			{
				"internalType": "address",
				"name": "sender",
				"type": "address"
			},
			{
				"internalType": "address",
				"name": "recipient",
				"type": "address"
			},
			{
				"internalType": "uint256",
				"name": "amount",
				"type": "uint256"
			}
		],
		"name": "transferFrom",
		"outputs": [
			{
				"internalType": "bool",
				"name": "",
				"type": "bool"
			}
		],
		"stateMutability": "nonpayable",
		"type": "function"
	},
	{
		"inputs": [
			{
				"internalType": "address",
				"name": "newOwner",
				"type": "address"
			}
		],
		"name": "transferOwnership",
		"outputs": [],
		"stateMutability": "nonpayable",
		"type": "function"
	},
	{
		"stateMutability": "payable",
		"type": "receive"
	}
]